[{"id":1,"category":"Javascript","title":"To what evaluates typeof a and typeof b in the following snippet:","info":"function foo() { \n let a = b = 0; \n a++; \n return a; \n } \n foo(); \n typeof a; // => ??? \n typeof b; // => ???","answer":"undefined, number"},{"id":2,"category":"Javascript","title":"To what evaluates typeof a and typeof b in the following snippet:","info":"function foo() { \n let a = b = 0; \n a++; \n return a; \n } \n\n foo();\n typeof a; // => ??? \n typeof b; // => ??? \n","answer":"typeof a;  // => 'undefined' \n typeof b;  // => 'number'"}]